puremysql/__init__.py
puremysql/logger.py
puremysql/pure_mysql.py
puremysql/pure_table.py
puremysql/sql_builder.py
puremysql/sql_builder_util.py
puremysql/util.py
puremysql/version.py
PureMySQL-0.0.10.dist-info/METADATA
PureMySQL-0.0.10.dist-info/WHEEL
PureMySQL-0.0.10.dist-info/top_level.txt
PureMySQL-0.0.10.dist-info/zip-safe
PureMySQL-0.0.10.dist-info/RECORD
