Metadata-Version: 2.1
Name: PureMySQL
Version: 0.0.10
Summary: 一个MySQL简单操作方式
Home-page: https://github.com/mouday/PureMySQL
Author: Peng Shiyu
Author-email: pengshiyuyx@gmail.com
License: MIT
Keywords: pure mysql
Platform: UNKNOWN
Classifier: Programming Language :: Python :: 3
Classifier: Programming Language :: Python :: 3.6
Classifier: Programming Language :: Python :: 2.7
Requires-Dist: mysql-connector-python (>=8.0.16)
Requires-Dist: six (>=1.12.0)
